typecho_password/__init__.py
typecho_password/main.py
typecho_password-0.0.1.dist-info/LICENSE
typecho_password-0.0.1.dist-info/METADATA
typecho_password-0.0.1.dist-info/WHEEL
typecho_password-0.0.1.dist-info/top_level.txt
typecho_password-0.0.1.dist-info/RECORD
