Metadata-Version: 2.1
Name: typecho-password
Version: 0.0.1
Project-URL: Homepage, https://github.com/veoco/typecho-password
Project-URL: Bug Tracker, https://github.com/veoco/typecho-password/issues
Classifier: Programming Language :: Python :: 3
Classifier: Operating System :: OS Independent
Requires-Python: >=3.9
License-File: LICENSE
